<?xml version="1.0" encoding="UTF-8" ?> 
<page layout="pixels" style="background-color:yellow;width:350px;height:250px;">

	<modules>

		<choiceModule id="n34" left="10" top="10" width="250" height="180">
			<choice isMulti="true"/>
			<option value="5">To jest opcja pierwsza za 5 punktów</option>
			<option value="0">To jest opcja druga za 0 punktów</option>
			<option value="1">To jest opcja trzecia za 1 punkt</option>
		</choiceModule>

		<buttonModule  left="300" top="0" width="50" height="50" style="">
			<button type="cancel" text=""/>
		</buttonModule>
		
	</modules>

</page>
