<?xml version='1.0' encoding='UTF-8' ?>

<addon id='Quiz' xmlns="http://icplayer.com" xmlns:xsi="http://www.w3.org/2001/XMLSchema-instance" xsi:schemaLocation="http://icplayer.com ../../tools/addon.xsd">
	<model>
		<property name="Questions" nameLabel="Quiz_property_Questions" type="list" isDefault="true">
			<property name="Question" nameLabel="Quiz_property_Question" type="html" isLocalized="true" />
			<property name="CorrectAnswer" nameLabel="Quiz_property_CorrectAnswer" type="string" />
			<property name="WrongAnswer1" nameLabel="Quiz_property_WrongAnswer1" type="string" />
			<property name="WrongAnswer2" nameLabel="Quiz_property_WrongAnswer2" type="string" />
			<property name="WrongAnswer3" nameLabel="Quiz_property_WrongAnswer3" type="string" />
			<property name="Hint" nameLabel="Quiz_property_hint" type="html" isLocalized="true" />
		</property>
		<property name="ShowHelpButtons" nameLabel="Quiz_property_ShowHelpButtons" type="boolean" />
		<property name="GameLostMessage" nameLabel="Quiz_property_GameLostMessage" type="html" isLocalized="true" />
		<property name="GameWonMessage" nameLabel="Quiz_property_GameWonMessage" type="html" isLocalized="true" />
        <property name="isActivity" nameLabel="Quiz_property_isActivity" type="boolean" />
	</model>
</addon>